pydbms/__init__.py
jodDB-0.0.1.dist-info/License.txt
jodDB-0.0.1.dist-info/METADATA
jodDB-0.0.1.dist-info/WHEEL
jodDB-0.0.1.dist-info/top_level.txt
jodDB-0.0.1.dist-info/RECORD
